streamlit_msal_2/__init__.py
streamlit_msal_2-0.2.1.dist-info/LICENSE
streamlit_msal_2-0.2.1.dist-info/METADATA
streamlit_msal_2-0.2.1.dist-info/WHEEL
streamlit_msal_2-0.2.1.dist-info/top_level.txt
streamlit_msal_2-0.2.1.dist-info/RECORD
