Metadata-Version: 2.1
Name: streamlit-msal-2
Version: 0.2.1
Summary: yet another msal Single-Sign-On module of streamlit applications also for ConfidentialClientApplication by checking required App roles of signed-in users in the enterprise setup, and support obo flow
Author-email: xiepei1 <cn_xiepei@163.com>
Project-URL: Repository, https://github.com/xiepei1/streamlit-msal-2
Project-URL: Homepage, https://github.com/xiepei1/streamlit-msal-2
Project-URL: Issues, https://github.com/xiepei1/streamlit-msal-2/issues
Project-URL: Documentation, https://xiepei1.github.io/streamlit-msal-2/
Classifier: Programming Language :: Python :: 3.10
Classifier: Programming Language :: Python :: 3.11
Classifier: Programming Language :: Python :: 3.12
Classifier: License :: OSI Approved :: MIT License
Classifier: Operating System :: OS Independent
Requires-Python: >=3.10
License-File: LICENSE
Requires-Dist: streamlit
Requires-Dist: streamlit-msal
Requires-Dist: loguru
